andrew_is_hungry_for_py/__init__.py
andrew_is_hungry_for_py/eat.py
andrew_is_hungry_for_py-0.0.3.dist-info/LICENSE
andrew_is_hungry_for_py-0.0.3.dist-info/METADATA
andrew_is_hungry_for_py-0.0.3.dist-info/WHEEL
andrew_is_hungry_for_py-0.0.3.dist-info/top_level.txt
andrew_is_hungry_for_py-0.0.3.dist-info/RECORD
