Metadata-Version: 2.1
Name: andrew-is-hungry-for-py
Version: 0.0.3
Summary: Learning how to publish to PyPi
Home-page: https://github.com/AndrewLane/andrew-is-hungry-for-py
Author: Andrew Lane
Author-email: andrew.w.lane@gmail.com
License: UNKNOWN
Platform: UNKNOWN
Classifier: Programming Language :: Python :: 3
Classifier: License :: OSI Approved :: MIT License
Classifier: Operating System :: OS Independent
Requires-Python: >=3.6
